[
    {
        "issuer_name": "Алкалоид Берово",
        "code": "ALKB"
    },
    {
        "issuer_name": "АТП Пролетер Крива Паланка",
        "code": "ATPP"
    },
    {
        "issuer_name": "Текстил Елма Прилеп",
        "code": "BIKF"
    },
    {
        "issuer_name": "Централен депозитар за хартии од вредност",
        "code": "CDHV"
    },
    {
        "issuer_name": "Единство Струга",
        "code": "EDST"
    },
    {
        "issuer_name": "Елмар Штип",
        "code": "ELMA"
    },
    {
        "issuer_name": "Еленица АД Струмица",
        "code": "ELNC"
    },
    {
        "issuer_name": "Енергомонт Скопје",
        "code": "ENER"
    },
    {
        "issuer_name": "Енса Брокер АД Скопје",
        "code": "ENSA"
    },
    {
        "issuer_name": "Еуромак брокер АД Скопје",
        "code": "EUMK"
    },
    {
        "issuer_name": "ФК Струга-Трим-Лум АД Струга",
        "code": "FKTL"
    },
    {
        "issuer_name": "Фротирка компани АД Делчево",
        "code": "FROT"
    },
    {
        "issuer_name": "Галеб АД Охрид",
        "code": "GALE"
    },
    {
        "issuer_name": "ЗИК Градиште Куманово",
        "code": "GDKM"
    },
    {
        "issuer_name": "Град. институт Македонија Скопје",
        "code": "GIMS"
    },
    {
        "issuer_name": "Градинар Охрид",
        "code": "GRDN"
    },
    {
        "issuer_name": "Градинар Свети Николе",
        "code": "GRSN"
    },
    {
        "issuer_name": "Институт за заварув. Југ Скопје",
        "code": "IJUG"
    },
    {
        "issuer_name": "Иново Брокер АД Скопје",
        "code": "INOV"
    },
    {
        "issuer_name": "Јавор Консалтинг Битола",
        "code": "JAKO"
    },
    {
        "issuer_name": "Југотутун Скопје",
        "code": "JUSK"
    },
    {
        "issuer_name": "Караорман Скопје",
        "code": "KARO"
    },
    {
        "issuer_name": "НЛБ Фондови АД Скопје",
        "code": "KDFO"
    },
    {
        "issuer_name": "КК Струмица 2022 АД Струмица",
        "code": "KKST"
    },
    {
        "issuer_name": "Комунапроект Тетово",
        "code": "KMPR"
    },
    {
        "issuer_name": "Стоковна куќа Корзо Битола",
        "code": "KORZ"
    },
    {
        "issuer_name": "Култура АД Скопје",
        "code": "KULT"
    },
    {
        "issuer_name": "Квасара Битола",
        "code": "KVAS"
    },
    {
        "issuer_name": "Лајон Инс АД Скопје",
        "code": "LAJO"
    },
    {
        "issuer_name": "Лихнида Охрид",
        "code": "LHND"
    },
    {
        "issuer_name": "ФК Македонија Ѓорче Петров - 1932 АД Скопје",
        "code": "MAGP"
    },
    {
        "issuer_name": "Македонска берза АД Скопје",
        "code": "MB"
    },
    {
        "issuer_name": "Млекара АД Битола",
        "code": "MLKR"
    },
    {
        "issuer_name": "Макпетрол-Теас АД Скопје",
        "code": "MPTE"
    },
    {
        "issuer_name": "Полиса Плус АД Скопје",
        "code": "OBPP"
    },
    {
        "issuer_name": "Вега осигурување АД Скопје",
        "code": "OMOS"
    },
    {
        "issuer_name": "Опфолио АД Скопје",
        "code": "OPFO"
    },
    {
        "issuer_name": "Очна оптика Геталдус Скопје",
        "code": "OPTK"
    },
    {
        "issuer_name": "Осигурителна полиса Скопје",
        "code": "OSPO"
    },
    {
        "issuer_name": "Пелагонија Комерц АД Битола",
        "code": "PELK"
    },
    {
        "issuer_name": "Пелагонија Гостивар",
        "code": "PGGV"
    },
    {
        "issuer_name": "Просветно дело Скопје",
        "code": "PROD"
    },
    {
        "issuer_name": "Протектор АД Прилеп",
        "code": "PROT"
    },
    {
        "issuer_name": "Роман АД Прилеп",
        "code": "PTRS"
    },
    {
        "issuer_name": "РИМИ АД Штип",
        "code": "RIMI"
    },
    {
        "issuer_name": "Реинг Скопје",
        "code": "RINS"
    },
    {
        "issuer_name": "РЖ Скопје-Инженеринг Скопје",
        "code": "RZIZ"
    },
    {
        "issuer_name": "Индустријал Струма АД Струмица",
        "code": "SKON"
    },
    {
        "issuer_name": "Пивара Скопје АД Скопје",
        "code": "SKP"
    },
    {
        "issuer_name": "Солун 2001 Гевгелија",
        "code": "SOLN"
    },
    {
        "issuer_name": "Тајмиште АД Кичево - долгорочно суспендирано од котација",
        "code": "TAJM"
    },
    {
        "issuer_name": "Сава осигурување АД Скопје",
        "code": "TBKO"
    },
    {
        "issuer_name": "Факул.-земјо. стопанство Трубарево АД с. Трубарево Скопје",
        "code": "TRUB"
    },
    {
        "issuer_name": "Трготекстил заед. служ. Скопје",
        "code": "TSZS"
    },
    {
        "issuer_name": "ВФП Фонд Менаџмент АД Скопје",
        "code": "VFPM"
    },
    {
        "issuer_name": "Ветеринарно сточарски центар Куманово",
        "code": "VSC"
    },
    {
        "issuer_name": "ЗИМ Скопје",
        "code": "ZIMS"
    },
    {
        "issuer_name": "ЗУАС АД Скопје",
        "code": "ZUAS"
    }
]